clonekin/__init__.py
clonekin/request.py
clonekin/snpool.py
tcb_project-0.0.1.dist-info/LICENSE.txt
tcb_project-0.0.1.dist-info/METADATA
tcb_project-0.0.1.dist-info/WHEEL
tcb_project-0.0.1.dist-info/top_level.txt
tcb_project-0.0.1.dist-info/RECORD
