Metadata-Version: 2.1
Name: tcb-project
Version: 0.0.1
Summary: Collecting C.elegans WGS Data with obvious phenotype
Author: Guo_Zhengyang
Author-email: guozhengyang980525@yahoo.co.jp
License: MIT License
Platform: all
Classifier: Programming Language :: Python :: 3
Classifier: Development Status :: 4 - Beta
License-File: LICENSE.txt
Requires-Dist: pandas
